kkcoding/__init__.py
kkcoding-0.0.1.dist-info/LICENSE
kkcoding-0.0.1.dist-info/METADATA
kkcoding-0.0.1.dist-info/WHEEL
kkcoding-0.0.1.dist-info/entry_points.txt
kkcoding-0.0.1.dist-info/top_level.txt
kkcoding-0.0.1.dist-info/RECORD
