Metadata-Version: 2.1
Name: kkcoding
Version: 0.0.1
Summary: Command-line Interface for KKCoding.net
Home-page: https://github.com/wangxinhe2006/kkcoding-cli
Author: 汪心禾
Author-email: wangxinhe06@gmail.com
License: UNKNOWN
Platform: UNKNOWN
Classifier: Programming Language :: Python :: 3.5
Classifier: Programming Language :: Python :: 3.6
Classifier: Programming Language :: Python :: 3.7
Classifier: License :: OSI Approved :: GNU Affero General Public License v3 or later (AGPLv3+)
Classifier: Operating System :: OS Independent
Requires-Dist: requests (<3,>=2.4.2)
